README.txt
bootstrap.py
buildout.cfg
setup.cfg
setup.py
docs/HISTORY.txt
zopyx/__init__.py
zopyx.smartprintng.core.egg-info/PKG-INFO
zopyx.smartprintng.core.egg-info/SOURCES.txt
zopyx.smartprintng.core.egg-info/dependency_links.txt
zopyx.smartprintng.core.egg-info/entry_points.txt
zopyx.smartprintng.core.egg-info/namespace_packages.txt
zopyx.smartprintng.core.egg-info/not-zip-safe
zopyx.smartprintng.core.egg-info/requires.txt
zopyx.smartprintng.core.egg-info/top_level.txt
zopyx/smartprintng/__init__.py
zopyx/smartprintng/core/LICENSE.txt
zopyx/smartprintng/core/__init__.py
zopyx/smartprintng/core/adapters.py
zopyx/smartprintng/core/aggregation.py
zopyx/smartprintng/core/demo2.css
zopyx/smartprintng/core/header.txt
zopyx/smartprintng/core/highlevel.py
zopyx/smartprintng/core/integration.py
zopyx/smartprintng/core/interfaces.py
zopyx/smartprintng/core/logger.py
zopyx/smartprintng/core/meta.zcml
zopyx/smartprintng/core/renderer.py
zopyx/smartprintng/core/resources.py
zopyx/smartprintng/core/transformation.py
zopyx/smartprintng/core/zcml.py
zopyx/smartprintng/core/demo/README.txt
zopyx/smartprintng/core/demo/__init__.py
zopyx/smartprintng/core/demo/demo.html
zopyx/smartprintng/core/demo/demo_app.py
zopyx/smartprintng/core/demo/index.html
zopyx/smartprintng/core/demo/resources/demo_styles.css
zopyx/smartprintng/core/demo/resources/demo_template.pt
zopyx/smartprintng/core/demo/resources/fop_styles.css
zopyx/smartprintng/core/demo/resources/resources.ini
zopyx/smartprintng/core/demo2/README.txt
zopyx/smartprintng/core/demo2/__init__.py
zopyx/smartprintng/core/demo2/demo_app.py
zopyx/smartprintng/core/demo2/resources/business_card.css
zopyx/smartprintng/core/demo2/resources/business_card2.css
zopyx/smartprintng/core/demo2/resources/business_card_template.pt
zopyx/smartprintng/core/demo2/resources/debug.css
zopyx/smartprintng/core/demo2/resources/resources.ini
zopyx/smartprintng/core/demo2/resources/zopyx1.png
zopyx/smartprintng/core/demo3/__init__.py
zopyx/smartprintng/core/demo3/demo_app.py
zopyx/smartprintng/core/tests/__init__.py
zopyx/smartprintng/core/tests/test.pt
zopyx/smartprintng/core/tests/testAdapters.py
zopyx/smartprintng/core/tests/testAggregation.py
zopyx/smartprintng/core/tests/testRenderer.py
zopyx/smartprintng/core/tests/testResources.py
zopyx/smartprintng/core/tests/testTransformation.py
