Metadata-Version: 1.0
Name: zopyx.smartprintng.core
Version: 2.0.0
Summary: SmartPrintNG core engine
Home-page: UNKNOWN
Author: Andreas Jung
Author-email: info@zopyx.com
License: ZPL
Keywords: SmartPrintNG Zope Python
Platform: UNKNOWN
Classifier: Programming Language :: Python
Classifier: Topic :: Software Development :: Libraries :: Python Modules
